infi.gevent_utils-0.2.8-py3.7-nspkg.pth
infi/gevent_utils/__init__.py
infi/gevent_utils/__version__.py
infi/gevent_utils/deferred.py
infi/gevent_utils/gevent_loop.py
infi/gevent_utils/glob.py
infi/gevent_utils/json_utils.py
infi/gevent_utils/safe_greenlets.py
infi/gevent_utils/shutil.py
infi/gevent_utils/silent_greenlets.py
infi/gevent_utils/tempfile.py
infi/gevent_utils/os/__init__.py
infi/gevent_utils/os/path.py
infi.gevent_utils-0.2.8.dist-info/LICENSE
infi.gevent_utils-0.2.8.dist-info/METADATA
infi.gevent_utils-0.2.8.dist-info/WHEEL
infi.gevent_utils-0.2.8.dist-info/entry_points.txt
infi.gevent_utils-0.2.8.dist-info/namespace_packages.txt
infi.gevent_utils-0.2.8.dist-info/top_level.txt
infi.gevent_utils-0.2.8.dist-info/RECORD
