Metadata-Version: 2.1
Name: infi.gevent-utils
Version: 0.2.8
Summary: gevent-utils
Home-page: https://github.com/Infinidat/infi.gevent_utils
Author: Arnon Yaari
Author-email: arnony@infinidat.com
License: BSD
Platform: UNKNOWN
Classifier: Intended Audience :: Developers
Classifier: Intended Audience :: System Administrators
Classifier: License :: OSI Approved :: BSD License
Classifier: Operating System :: OS Independent
Classifier: Programming Language :: Python :: 2
Classifier: Programming Language :: Python :: 3
Classifier: Topic :: Software Development :: Libraries :: Python Modules
Requires-Dist: gevent
Requires-Dist: infi.pyutils
Requires-Dist: infi.traceback
Requires-Dist: logbook
Requires-Dist: setuptools
Requires-Dist: six
